{
    "asset": {
        "format": "jpg",
        "id": "1e8b13a57a13c37a13deb0eb8b1f6803",
        "name": "Ren-Chuanfeng-Zhou-Kun-56_1589729935.jpg",
        "path": "file:D:/Bilder/Sprite_DB/Sprites/Ren-Chuanfeng-Zhou-Kun-56_1589729935.jpg",
        "size": {
            "width": 1528,
            "height": 822
        },
        "state": 2,
        "type": 1
    },
    "regions": [
        {
            "id": "h9irnN25P",
            "type": "RECTANGLE",
            "tags": [
                "RedSprite"
            ],
            "boundingBox": {
                "height": 112.27316199113268,
                "width": 68.73851921274601,
                "left": 439.6401124648547,
                "top": 428.7753788752008
            },
            "points": [
                {
                    "x": 439.6401124648547,
                    "y": 428.7753788752008
                },
                {
                    "x": 508.3786316776007,
                    "y": 428.7753788752008
                },
                {
                    "x": 508.3786316776007,
                    "y": 541.0485408663334
                },
                {
                    "x": 439.6401124648547,
                    "y": 541.0485408663334
                }
            ]
        },
        {
            "id": "LI-ZL5CeG",
            "type": "RECTANGLE",
            "tags": [
                "RedSprite"
            ],
            "boundingBox": {
                "height": 148.93379790940767,
                "width": 66.44727020120665,
                "left": 496.9222118088097,
                "top": 346.28900268767353
            },
            "points": [
                {
                    "x": 496.9222118088097,
                    "y": 346.28900268767353
                },
                {
                    "x": 563.3694820100163,
                    "y": 346.28900268767353
                },
                {
                    "x": 563.3694820100163,
                    "y": 495.2228005970812
                },
                {
                    "x": 496.9222118088097,
                    "y": 495.2228005970812
                }
            ]
        },
        {
            "id": "pjBUCryAD",
            "type": "RECTANGLE",
            "tags": [
                "RedSprite"
            ],
            "boundingBox": {
                "height": 152.37072296674242,
                "width": 90.50573444455834,
                "left": 586.2823217475984,
                "top": 411.5907098856537
            },
            "points": [
                {
                    "x": 586.2823217475984,
                    "y": 411.5907098856537
                },
                {
                    "x": 676.7880561921567,
                    "y": 411.5907098856537
                },
                {
                    "x": 676.7880561921567,
                    "y": 563.9614328523961
                },
                {
                    "x": 586.2823217475984,
                    "y": 563.9614328523961
                }
            ]
        },
        {
            "id": "SdPOz2lv5",
            "type": "RECTANGLE",
            "tags": [
                "RedSprite"
            ],
            "boundingBox": {
                "height": 187.88577546973676,
                "width": 59.5734357610413,
                "left": 674.4967197750702,
                "top": 365.76492591352826
            },
            "points": [
                {
                    "x": 674.4967197750702,
                    "y": 365.76492591352826
                },
                {
                    "x": 734.0701555361115,
                    "y": 365.76492591352826
                },
                {
                    "x": 734.0701555361115,
                    "y": 553.6507013832651
                },
                {
                    "x": 674.4967197750702,
                    "y": 553.6507013832651
                }
            ]
        },
        {
            "id": "p212UGWma",
            "type": "RECTANGLE",
            "tags": [
                "RedSprite"
            ],
            "boundingBox": {
                "height": 185.59443382768265,
                "width": 69.88414371851569,
                "left": 726.0506091846297,
                "top": 363.4736716772206
            },
            "points": [
                {
                    "x": 726.0506091846297,
                    "y": 363.4736716772206
                },
                {
                    "x": 795.9347529031454,
                    "y": 363.4736716772206
                },
                {
                    "x": 795.9347529031454,
                    "y": 549.0681055049032
                },
                {
                    "x": 726.0506091846297,
                    "y": 549.0681055049032
                }
            ]
        },
        {
            "id": "2hAJ5l9o0",
            "type": "RECTANGLE",
            "tags": [
                "RedSprite"
            ],
            "boundingBox": {
                "height": 161.53591472346608,
                "width": 67.59289470697634,
                "left": 806.2455482661668,
                "top": 353.1628528023431
            },
            "points": [
                {
                    "x": 806.2455482661668,
                    "y": 353.1628528023431
                },
                {
                    "x": 873.8384429731431,
                    "y": 353.1628528023431
                },
                {
                    "x": 873.8384429731431,
                    "y": 514.6987675258091
                },
                {
                    "x": 806.2455482661668,
                    "y": 514.6987675258091
                }
            ]
        }
    ],
    "version": "2.2.0"
}