{
    "asset": {
        "format": "jpg",
        "id": "44feb7e64f12b485291f27b123b40602",
        "name": "IMG_4661_ll-low-light.jpg",
        "path": "file:D:/Bilder/Sprite_DB/Sprites/IMG_4661_ll-low-light.jpg",
        "size": {
            "width": 5317,
            "height": 2988
        },
        "state": 2,
        "type": 1
    },
    "regions": [
        {
            "id": "YhhwBXqNw",
            "type": "RECTANGLE",
            "tags": [
                "RedSprite"
            ],
            "boundingBox": {
                "height": 270.91212158203126,
                "width": 370.74501387963477,
                "left": 2363.000435712076,
                "top": 1722.1462500000002
            },
            "points": [
                {
                    "x": 2363.000435712076,
                    "y": 1722.1462500000002
                },
                {
                    "x": 2733.7454495917104,
                    "y": 1722.1462500000002
                },
                {
                    "x": 2733.7454495917104,
                    "y": 1993.0583715820314
                },
                {
                    "x": 2363.000435712076,
                    "y": 1993.0583715820314
                }
            ]
        }
    ],
    "version": "2.2.0"
}